{
    "comment": "\nDistance: 1350 Conditions: Overall very good conditions and flat water.  Very slight cross wind but consistent for all races.  Thanks to Berwick for making the trip!\n\nNone",
    "day": "2025-04-05",
    "heats": [
        {
            "class": "fours",
            "gender": "boys",
            "results": [
                {
                    "margin_from_winner": 0,
                    "raw_time": "4:38.2",
                    "school": "BB&N"
                },
                {
                    "margin_from_winner": 7.6,
                    "raw_time": "4:45.8",
                    "school": "Berwick"
                }
            ],
            "varsity_index": "1"
        },
        {
            "class": "fours",
            "gender": "boys",
            "results": [
                {
                    "margin_from_winner": 0,
                    "raw_time": "4:50.5",
                    "school": "BB&N"
                },
                {
                    "margin_from_winner": 32.6,
                    "raw_time": "5:23.1",
                    "school": "Berwick"
                }
            ],
            "varsity_index": "2"
        },
        {
            "class": "fours",
            "gender": "boys",
            "results": [
                {
                    "margin_from_winner": 0,
                    "raw_time": "5:14.7",
                    "school": "BB&N"
                },
                {
                    "margin_from_winner": 18.0,
                    "raw_time": "5:32.7",
                    "school": "Berwick"
                }
            ],
            "varsity_index": "3"
        },
        {
            "class": "fours",
            "gender": "girls",
            "results": [
                {
                    "margin_from_winner": 0,
                    "raw_time": "5:12",
                    "school": "BB&N"
                },
                {
                    "margin_from_winner": 78.0,
                    "raw_time": "6:30",
                    "school": "Berwick"
                }
            ],
            "varsity_index": "1"
        }
    ],
    "regatta_display_name": "NEIRA Boys & Girls Fours,BB&N vs. Berwick Academy",
    "url": "https://www.row2k.com/results/resultspage.cfm?UID=CE456225129ACDB361E1BEAB29CB57A4&cat=5"
}